Metadata-Version: 2.4
Name: xingshu_sqlite
Version: 0.0.1
Summary: 星枢(xingshu)框架的SQLite数据库接口
Author-email: bhzy <2024305928@qq.com>
License-Expression: MIT
Project-URL: Homepage, https://github.com/bhzyxyqy/xingshu
Project-URL: Issues, https://github.com/bhzyxyqy/xingshu/issues
Classifier: Programming Language :: Python :: 3
Classifier: Operating System :: OS Independent
Requires-Python: >=3.8
License-File: LICENSE
Requires-Dist: importlib_metadata==8.6.1
Requires-Dist: peewee==3.17.9
Dynamic: license-file
